glowplug/__init__.py
glowplug/config/__init__.py
glowplug/driver/__init__.py
glowplug/driver/base.py
glowplug/driver/mssql.py
glowplug/driver/pg.py
glowplug/driver/sqlite.py
python_glowplug-0.3.12.dist-info/LICENSE
python_glowplug-0.3.12.dist-info/METADATA
python_glowplug-0.3.12.dist-info/WHEEL
python_glowplug-0.3.12.dist-info/RECORD
